pyarcfire/__init__.py
pyarcfire/__main__.py
pyarcfire/_typing.py
pyarcfire/array_utils.py
pyarcfire/assert_utils.py
pyarcfire/cluster.py
pyarcfire/debug_utils.py
pyarcfire/finder.py
pyarcfire/log_utils.py
pyarcfire/matrix_utils.py
pyarcfire/merge.py
pyarcfire/merge_fit.py
pyarcfire/orientation.py
pyarcfire/preprocess.py
pyarcfire/similarity.py
pyarcfire/arc/__init__.py
pyarcfire/arc/common.py
pyarcfire/arc/fit.py
pyarcfire/arc/functions.py
pyarcfire/arc/utils.py
pyarcfire-0.1.1.dist-info/METADATA
pyarcfire-0.1.1.dist-info/WHEEL
pyarcfire-0.1.1.dist-info/licenses/LICENSE.txt
pyarcfire-0.1.1.dist-info/RECORD
