Metadata-Version: 2.3
Name: pyarcfire
Version: 0.1.1
Summary: A port of SpArcFiRe, a spiral arc finder
Project-URL: Source, https://github.com/pavyamsiri/pyarcfire.git
Project-URL: Issues, https://github.com/pavyamsiri/pyarcfire/issues
Author: Pavadol Yamsiri
License: BSD 3-Clause License
Keywords: arc,astronomy,finder,spiral
Classifier: Development Status :: 2 - Pre-Alpha
Classifier: Intended Audience :: Science/Research
Classifier: License :: OSI Approved :: BSD License
Classifier: Programming Language :: Python :: 3.10
Classifier: Topic :: Scientific/Engineering :: Astronomy
Requires-Python: >=3.10.15
Requires-Dist: numpy>=1.2
Requires-Dist: optype>=0.6.1
Requires-Dist: scikit-image>=0.18
Requires-Dist: scipy>=1.14
Requires-Dist: typing-extensions>=3.10
